{
    "env": "development",
    "dbConfig": {
        "host": "localhost",
        "user": "root",
        "password": "password",
        "database": "test",
        "port": 3306
    },
    "secretKey": "secretKey",
    "log": {
        "format": "dev",
        "dir": "../logs"
    },
    "cors": {
        "origin": true,
        "credentials": true
    },
    "sigFox": {
        "api_url": "https://api.sigfox.com/v2/",
        "basic_username": "613716e8e833d954dcd18878",
        "basic_password": "9144f051f08bace6173f9ba894e57875"
    }
}